wsgi_cloudflare_proxy_fix.py
wsgi_cloudflare_proxy_fix-0.1.2.dist-info/METADATA
wsgi_cloudflare_proxy_fix-0.1.2.dist-info/WHEEL
wsgi_cloudflare_proxy_fix-0.1.2.dist-info/RECORD
