Metadata-Version: 2.1
Name: wsgi-cloudflare-proxy-fix
Version: 0.1.2
Summary: Sets REMOTE_ADDR to the correct value when behind Cloudflare, based on the Cf-Connecting-Ip header, when requests originate from Cloudflare's IP range.
Home-page: https://github.com/wolever/wsgi-cloudflare-proxy-fix
Author: David Wolever
Author-email: david@wolever.net
Requires-Python: >=3.9,<4.0
Classifier: Programming Language :: Python :: 3
Classifier: Programming Language :: Python :: 3.9
Classifier: Programming Language :: Python :: 3.10
Classifier: Programming Language :: Python :: 3.11
